pyact/__base__.py
pyact/__init__.py
pyact/license_reference.txt
pyact/demos/hello_goodbye/hello_goodbye.html
pyact/demos/hello_goodbye/hello_goodbye.py
pyact/demos/hello_goodbye/__target__/hello_goodbye.js
pyact/demos/hello_goodbye/__target__/hello_goodbye.map
pyact/demos/hello_goodbye/__target__/hello_goodbye.pretty.map
pyact/demos/hello_goodbye/__target__/hello_goodbye.project
pyact/demos/hello_goodbye/__target__/hello_goodbye.py
pyact/demos/hello_goodbye/__target__/org.transcrypt.__runtime__.js
pyact/demos/hello_goodbye/__target__/org.transcrypt.__runtime__.map
pyact/demos/hello_goodbye/__target__/org.transcrypt.__runtime__.pretty.map
pyact/demos/hello_goodbye/__target__/org.transcrypt.__runtime__.py
pyact/demos/hello_goodbye/__target__/pyreact.js
pyact/demos/hello_goodbye/__target__/pyreact.map
pyact/demos/hello_goodbye/__target__/pyreact.pretty.map
pyact/demos/hello_goodbye/__target__/pyreact.py
Pyact-0.0.2.dist-info/LICENSE
Pyact-0.0.2.dist-info/METADATA
Pyact-0.0.2.dist-info/WHEEL
Pyact-0.0.2.dist-info/top_level.txt
Pyact-0.0.2.dist-info/RECORD
