Metadata-Version: 2.1
Name: Pyact
Version: 0.0.2
Summary: A React API for Transcrypt
Home-page: https://github.com/QQuick/Pyact
Author: Jacques de Hooge
Author-email: jacques.de.hooge@qquick.org
License: Apache 2.0
Keywords: transcrypt,react,python,browser
Platform: UNKNOWN
Classifier: Development Status :: 2 - Pre-Alpha
Classifier: Intended Audience :: Developers
Classifier: Natural Language :: English
Classifier: License :: OSI Approved :: Apache Software License
Classifier: Topic :: Software Development :: Libraries :: Python Modules
Classifier: Operating System :: OS Independent
Classifier: Programming Language :: Python :: 3.9
Requires-Dist: transcrypt
